bootgraph/__init__.py
bootgraph/database/__init__.py
bootgraph/database/filter_builders/__init__.py
bootgraph/database/operations.py
bootgraph/database/utils.py
bootgraph/dl.py
bootgraph/models.py
bootgraph/router.py
bootgraph/schemas/__init__.py
bootgraph/schemas/generators.py
bootgraph/schemas/models.py
bootgraph/setup.py
bootgraph-1.18.0.dist-info/METADATA
bootgraph-1.18.0.dist-info/WHEEL
bootgraph-1.18.0.dist-info/licenses/LICENSE
bootgraph-1.18.0.dist-info/RECORD
