Metadata-Version: 2.4
Name: bootgraph
Version: 1.18.0
Summary: A Python library for integrating SQLModel and Strawberry, providing a seamless GraphQL integration with FastAPI and advanced features for database interactions.
License: MIT
License-File: LICENSE
Author: Matheus Doreto
Author-email: matheusdoreto.md@gmail.com
Requires-Python: >=3.12,<4.0
Classifier: Development Status :: 5 - Production/Stable
Classifier: Framework :: FastAPI
Classifier: Intended Audience :: Developers
Classifier: License :: OSI Approved :: MIT License
Classifier: Natural Language :: English
Classifier: Programming Language :: Python :: 3
Classifier: Programming Language :: Python :: 3.12
Classifier: Programming Language :: Python :: 3.13
Classifier: Programming Language :: Python :: 3.14
Classifier: Topic :: Database
Classifier: Topic :: Database :: Database Engines/Servers
Requires-Dist: black (>=24.10.0,<25.0.0)
Requires-Dist: fastapi (>=0.121.1,<0.122.0)
Requires-Dist: sqlmodel (>=0.0.27,<0.0.28)
Requires-Dist: strawberry-graphql[debug-server] (>=0.284.2,<0.285.0)
Project-URL: Bug Tracker, https://github.com/MDoreto/graphemy/issues
Project-URL: Documentation, https://graphemy.readthedocs.io/en/latest/
Project-URL: Homepage, https://github.com/MDoreto/graphemy
Project-URL: Repository, https://github.com/MDoreto/graphemy
